deepfinder/__init__.py
deepfinder/inference.py
deepfinder/losses.py
deepfinder/models.py
deepfinder/training.py
deepfinder/commands/__init__.py
deepfinder/commands/convert_tiff_to_h5.py
deepfinder/commands/detect_spots.py
deepfinder/commands/detect_spots_with_atlas.py
deepfinder/commands/exodeepfinder.py
deepfinder/commands/generate_annotation.py
deepfinder/commands/generate_segmentation.py
deepfinder/commands/merge_detector_expert.py
deepfinder/commands/segment.py
deepfinder/commands/structure_training_dataset.py
deepfinder/commands/train.py
deepfinder/commands/utils.py
deepfinder/utils/__init__.py
deepfinder/utils/common.py
deepfinder/utils/core.py
deepfinder/utils/dataloader.py
deepfinder/utils/eval.py
deepfinder/utils/objl.py
deepfinder/utils/params.py
deepfinder/utils/smap.py
exodeepfinder-0.3.14.dist-info/LICENSE
exodeepfinder-0.3.14.dist-info/METADATA
exodeepfinder-0.3.14.dist-info/WHEEL
exodeepfinder-0.3.14.dist-info/entry_points.txt
exodeepfinder-0.3.14.dist-info/top_level.txt
exodeepfinder-0.3.14.dist-info/RECORD
